ccdxt/__init__.py
ccdxt-0.1.dist-info/LICENSE
ccdxt-0.1.dist-info/METADATA
ccdxt-0.1.dist-info/WHEEL
ccdxt-0.1.dist-info/top_level.txt
ccdxt-0.1.dist-info/RECORD
