Metadata-Version: 2.1
Name: ccdxt
Version: 0.1
Summary: Python DEX trading API
Home-page: https://github.com/MunSunouk
Author: Mun Sunouk
Author-email: mun_sunouk@gmail.com
License: MIT
Keywords: python,api,library,crypto,decentralized,blockchain,cryptocurrency,swap,trade,arbitrage,dex,web3py
Classifier: Development Status :: 4 - Beta
Classifier: Intended Audience :: Developers
Classifier: Intended Audience :: Financial and Insurance Industry
Classifier: Intended Audience :: Information Technology
Classifier: Topic :: Software Development :: Build Tools
Classifier: Topic :: Office/Business :: Financial :: Investment
Classifier: License :: OSI Approved :: MIT License
Classifier: Programming Language :: Python :: 3.7
Classifier: Programming Language :: Python :: 3.8
Classifier: Programming Language :: Python :: 3.9
Classifier: Operating System :: OS Independent
Classifier: Environment :: Console
License-File: LICENSE
Requires-Dist: web3 (==5.31.0eth-tester==0.7.0b1)
